gen_stm32/__init__.py
gen_stm32/py.typed
gen_stm32/conf/gen_stm32.cfg
gen_stm32/conf/gen_stm32.logo
gen_stm32/conf/gen_stm32_util.cfg
gen_stm32/conf/project.yaml
gen_stm32/conf/template/build/Makefile.template
gen_stm32/conf/template/build/objects.template
gen_stm32/conf/template/build/sources.template
gen_stm32/conf/template/build/source/subdir.template
gen_stm32/conf/template/includes/CMSIS/arm_common_tables.template
gen_stm32/conf/template/includes/CMSIS/arm_math.template
gen_stm32/conf/template/includes/CMSIS/core_cm0.template
gen_stm32/conf/template/includes/CMSIS/core_cm3.template
gen_stm32/conf/template/includes/CMSIS/core_cm4.template
gen_stm32/conf/template/includes/CMSIS/core_cm4_simd.template
gen_stm32/conf/template/includes/CMSIS/core_cmFunc.template
gen_stm32/conf/template/includes/CMSIS/core_cmInstr.template
gen_stm32/conf/template/includes/STM32F4xx/stm32f4xx.template
gen_stm32/conf/template/includes/STM32F4xx/stm32f4xx_conf.template
gen_stm32/conf/template/includes/STM32F4xx/system_stm32f4xx.template
gen_stm32/conf/template/includes/STM32F4xx_StdPeriph_Driver/inc/misc.template
gen_stm32/conf/template/includes/STM32F4xx_StdPeriph_Driver/inc/stm32f4xx_adc.template
gen_stm32/conf/template/includes/STM32F4xx_StdPeriph_Driver/inc/stm32f4xx_can.template
gen_stm32/conf/template/includes/STM32F4xx_StdPeriph_Driver/inc/stm32f4xx_crc.template
gen_stm32/conf/template/includes/STM32F4xx_StdPeriph_Driver/inc/stm32f4xx_cryp.template
gen_stm32/conf/template/includes/STM32F4xx_StdPeriph_Driver/inc/stm32f4xx_dac.template
gen_stm32/conf/template/includes/STM32F4xx_StdPeriph_Driver/inc/stm32f4xx_dbgmcu.template
gen_stm32/conf/template/includes/STM32F4xx_StdPeriph_Driver/inc/stm32f4xx_dcmi.template
gen_stm32/conf/template/includes/STM32F4xx_StdPeriph_Driver/inc/stm32f4xx_dma.template
gen_stm32/conf/template/includes/STM32F4xx_StdPeriph_Driver/inc/stm32f4xx_exti.template
gen_stm32/conf/template/includes/STM32F4xx_StdPeriph_Driver/inc/stm32f4xx_flash.template
gen_stm32-1.2.4.dist-info/LICENSE
gen_stm32-1.2.4.dist-info/METADATA
gen_stm32-1.2.4.dist-info/WHEEL
gen_stm32-1.2.4.dist-info/top_level.txt
gen_stm32-1.2.4.dist-info/RECORD
